sentiment_words_arabic.py
sentiment_words-0.1.dist-info/METADATA
sentiment_words-0.1.dist-info/WHEEL
sentiment_words-0.1.dist-info/top_level.txt
sentiment_words-0.1.dist-info/RECORD
