Metadata-Version: 2.1
Name: sentiment_words
Version: 0.1
Summary: مكتبة الكلمات الإيجابية والسلبية.
Author: fouad attig algeria-2024
Author-email: fouad.dbz@gmail.com
Classifier: Programming Language :: Python :: 3
Classifier: License :: OSI Approved :: MIT License
Classifier: Operating System :: OS Independent
Requires-Python: >=3.6
